rabbitmq_auto_scaler/__init__.py
rabbitmq_auto_scaler/async_thread_worker.py
rabbitmq_auto_scaler/autoscaler.py
rabbitmq_auto_scaler/base_auto_scaler.py
rabbitmq_auto_scaler/connection_pool.py
rabbitmq_auto_scaler-0.1.2.dist-info/LICENSE
rabbitmq_auto_scaler-0.1.2.dist-info/METADATA
rabbitmq_auto_scaler-0.1.2.dist-info/WHEEL
rabbitmq_auto_scaler-0.1.2.dist-info/top_level.txt
rabbitmq_auto_scaler-0.1.2.dist-info/RECORD
