Metadata-Version: 2.1
Name: rabbitmq_auto_scaler
Version: 0.1.2
Summary: A library for auto-scaling RabbitMQ consumers
Home-page: https://github.com/Nishantth1/RabbitMQAutoScaler
Author: Nishant Thakre
Author-email: nishantthakre9@gmail.com
License: MIT
Classifier: Programming Language :: Python :: 3
Classifier: License :: OSI Approved :: MIT License
Classifier: Operating System :: OS Independent
Requires-Python: >=3.7
License-File: LICENSE
Requires-Dist: aio-pika
Requires-Dist: asyncio
